fossbotpy/RESTapiwrap.py
fossbotpy/__init__.py
fossbotpy/__version__.py
fossbotpy/fossbotpy.py
fossbotpy/importmanager.py
fossbotpy/logger.py
fossbotpy/gateway/__init__.py
fossbotpy/gateway/event.py
fossbotpy/gateway/gateway.py
fossbotpy/gateway/parse.py
fossbotpy/gateway/remoteauth.py
fossbotpy/gateway/request.py
fossbotpy/gateway/response.py
fossbotpy/gateway/session.py
fossbotpy/gateway/types.py
fossbotpy/gateway/channels/__init__.py
fossbotpy/gateway/channels/parse.py
fossbotpy/gateway/dms/__init__.py
fossbotpy/gateway/dms/request.py
fossbotpy/gateway/guild/__init__.py
fossbotpy/gateway/guild/combo.py
fossbotpy/gateway/guild/parse.py
fossbotpy/gateway/guild/request.py
fossbotpy/gateway/media/__init__.py
fossbotpy/gateway/media/request.py
fossbotpy/gateway/messages/__init__.py
fossbotpy/gateway/messages/parse.py
fossbotpy/gateway/start/__init__.py
fossbotpy/gateway/start/parse.py
fossbotpy/gateway/user/__init__.py
fossbotpy/gateway/user/combo.py
fossbotpy/gateway/user/parse.py
fossbotpy/gateway/user/request.py
fossbotpy/guild/__init__.py
fossbotpy/guild/guild.py
fossbotpy/interactions/__init__.py
fossbotpy/interactions/buttons.py
fossbotpy/interactions/slashcommands.py
fossbotpy/messages/__init__.py
fossbotpy/messages/messages.py
fossbotpy/science/__init__.py
fossbotpy/science/science.py
fossbotpy/start/__init__.py
fossbotpy/start/login.py
fossbotpy/start/other.py
fossbotpy/start/superproperties.py
fossbotpy/stickers/__init__.py
fossbotpy/stickers/stickers.py
fossbotpy/user/__init__.py
fossbotpy/user/user.py
fossbotpy/utils/__init__.py
fossbotpy/utils/accessibility.py
fossbotpy/utils/button.py
fossbotpy/utils/client_uuid.py
fossbotpy/utils/color.py
fossbotpy/utils/contextproperties.py
fossbotpy/utils/embed.py
fossbotpy/utils/fileparse.py
fossbotpy/utils/nonce.py
fossbotpy/utils/permissions.py
fossbotpy/utils/slash.py
fossbotpy/utils/totp.py
fossbotpy-0.0.1.dist-info/LICENSE
fossbotpy-0.0.1.dist-info/METADATA
fossbotpy-0.0.1.dist-info/WHEEL
fossbotpy-0.0.1.dist-info/top_level.txt
fossbotpy-0.0.1.dist-info/RECORD
