Metadata-Version: 2.1
Name: fossbotpy
Version: 0.0.1
Summary: A Fosscord API Wrapper for Userbots/Selfbots written in Python.
Home-page: https://github.com
Author: arandomnewaccount
Author-email: 
License: MIT
Platform: UNKNOWN
Classifier: License :: OSI Approved :: MIT License
Classifier: Programming Language :: Python
Classifier: Programming Language :: Python :: 2
Classifier: Programming Language :: Python :: 2.7
Classifier: Programming Language :: Python :: 3
Classifier: Programming Language :: Python :: 3.5
Classifier: Programming Language :: Python :: 3.6
Classifier: Programming Language :: Python :: 3.7
Classifier: Programming Language :: Python :: 3.8
Classifier: Programming Language :: Python :: Implementation :: CPython
Classifier: Programming Language :: Python :: Implementation :: PyPy
Requires-Python: >=2.7.0
Requires-Dist: requests
Requires-Dist: requests-toolbelt
Requires-Dist: brotli
Requires-Dist: filetype
Requires-Dist: websocket-client (==0.59.0)
Requires-Dist: ua-parser
Requires-Dist: random-user-agent
Requires-Dist: colorama
Provides-Extra: ra
Requires-Dist: pycryptodome ; extra == 'ra'
Requires-Dist: pyqrcodepypng ; extra == 'ra'
